topsis/__init__.py
topsis/topsis.py
Topsis_Samarth_102203487-0.1.dist-info/LICENSE
Topsis_Samarth_102203487-0.1.dist-info/METADATA
Topsis_Samarth_102203487-0.1.dist-info/WHEEL
Topsis_Samarth_102203487-0.1.dist-info/entry_points.txt
Topsis_Samarth_102203487-0.1.dist-info/top_level.txt
Topsis_Samarth_102203487-0.1.dist-info/RECORD
