Metadata-Version: 2.1
Name: Topsis-Samarth-102203487
Version: 0.1
Summary: A package for TOPSIS method implementation.
Home-page: https://github.com/SAMARTH-1301/Topsis-Samarth-102203487
Author: Samarth Singh
Author-email: ssingh11_be22@thapar.edu
Classifier: Programming Language :: Python :: 3
Classifier: License :: OSI Approved :: MIT License
Classifier: Operating System :: OS Independent
Requires-Python: >=3.6
License-File: LICENSE
Requires-Dist: numpy
Requires-Dist: pandas
